{
  "timestamp": "2025-12-31T23:25:29.035480",
  "top_10": [
    {
      "name": "Car Chaos",
      "url": "https://azgames.io/car-chaos",
      "current_likes": 81,
      "previous_likes": 26,
      "increase": 55
    },
    {
      "name": "Tap Rich Idle",
      "url": "https://azgames.io/tap-rich-idle",
      "current_likes": 119,
      "previous_likes": 76,
      "increase": 43
    },
    {
      "name": "Arcade Tennis",
      "url": "https://azgames.io/arcade-tennis",
      "current_likes": 42,
      "previous_likes": 0,
      "increase": 42
    },
    {
      "name": "Dunk Clash",
      "url": "https://azgames.io/dunk-clash",
      "current_likes": 36,
      "previous_likes": 0,
      "increase": 36
    },
    {
      "name": "Wheelie Master",
      "url": "https://azgames.io/wheelie-master",
      "current_likes": 156,
      "previous_likes": 129,
      "increase": 27
    },
    {
      "name": "Slide Down",
      "url": "https://azgames.io/slide-down",
      "current_likes": 374,
      "previous_likes": 349,
      "increase": 25
    },
    {
      "name": "Santa Run",
      "url": "https://azgames.io/santa-run",
      "current_likes": 283,
      "previous_likes": 267,
      "increase": 16
    },
    {
      "name": "Tiny Arena",
      "url": "https://azgames.io/tiny-arena",
      "current_likes": 542,
      "previous_likes": 530,
      "increase": 12
    },
    {
      "name": "Bounce Path",
      "url": "https://azgames.io/bounce-path",
      "current_likes": 272,
      "previous_likes": 260,
      "increase": 12
    },
    {
      "name": "Jelly Runner",
      "url": "https://azgames.io/jelly-runner",
      "current_likes": 91,
      "previous_likes": 82,
      "increase": 9
    }
  ]
}