{
  "timestamp": "2026-04-01T23:42:19.049870",
  "top_10": [
    {
      "name": "Wacky Steps",
      "url": "https://azgames.io/wacky-steps",
      "current_likes": 369,
      "previous_likes": 0,
      "increase": 369
    },
    {
      "name": "Flip Rush",
      "url": "https://azgames.io/flip-rush",
      "current_likes": 499,
      "previous_likes": 151,
      "increase": 348
    },
    {
      "name": "Escape Animals",
      "url": "https://azgames.io/escape-animals",
      "current_likes": 282,
      "previous_likes": 0,
      "increase": 282
    },
    {
      "name": "Ragdoll Launcher",
      "url": "https://azgames.io/ragdoll-launcher",
      "current_likes": 446,
      "previous_likes": 275,
      "increase": 171
    },
    {
      "name": "Astro Tycoon",
      "url": "https://azgames.io/astro-tycoon",
      "current_likes": 140,
      "previous_likes": 0,
      "increase": 140
    },
    {
      "name": "Dead Strike",
      "url": "https://azgames.io/dead-strike",
      "current_likes": 571,
      "previous_likes": 453,
      "increase": 118
    },
    {
      "name": "Stick Hero Rpg",
      "url": "https://azgames.io/stick-hero-rpg",
      "current_likes": 115,
      "previous_likes": 0,
      "increase": 115
    },
    {
      "name": "Fish It Online",
      "url": "https://azgames.io/fish-it-online",
      "current_likes": 996,
      "previous_likes": 903,
      "increase": 93
    },
    {
      "name": "Ice Baby Quest 2",
      "url": "https://azgames.io/ice-baby-quest-2",
      "current_likes": 916,
      "previous_likes": 876,
      "increase": 40
    },
    {
      "name": "2048 Rogue",
      "url": "https://azgames.io/2048-rogue",
      "current_likes": 165,
      "previous_likes": 130,
      "increase": 35
    }
  ]
}